{
  "version": {
    "current": "1.1.0",
    "minimum_required": "1.1.0"
  },
  "authorized_users": [
      {
      "name": "home",
      "hardware_id": "Qc014M2CuoOipADRXtetVcxuTku/HukfboPstKqBgo0=",
      "expiry_date": "2099-12-31"
    }, 
    {
      "name": "5080",
      "hardware_id": "rJNhIvHEMYNvsY4yHo0Y/ZzkuBHwLt6oCUusUw4Ur3E=",
      "expiry_date": "2099-12-31"
    },
    {
      "name": "1650",
      "hardware_id": "o+3R6hz0mo0rkNMupkXwin8ksOJMj0J0+AfwUtCNXRA=",
      "expiry_date": "2099-12-31"
    },
    {
      "name": "아귀 3.11.1",
      "hardware_id": "9Gf81CRyRDI3mc9jaXQs+rP84CWfQr+LBKdFz0BVXS0=",
      "expiry_date": "2026-12-31"
    },
    {
      "name": "아귀 3.13.5",
      "hardware_id": "Twde5c/C62NZtXWHMuynYW4JgZhHMvqZUcFvmnWV0tE=",
      "expiry_date": "2026-12-31"
    }
  ]
}
